fastapi_webserver-0.4.14.dist-info/licenses/LICENSE.md
webserver/__init__.py
webserver/config.py
webserver/core.py
webserver/env.py
webserver/frontend/__init__.py
webserver/frontend/css.py
webserver/http/__init__.py
webserver/http/headers.py
webserver/http/proxies.py
webserver/notifications/__init__.py
webserver/notifications/smtp.py
fastapi_webserver-0.4.14.dist-info/METADATA
fastapi_webserver-0.4.14.dist-info/WHEEL
fastapi_webserver-0.4.14.dist-info/top_level.txt
fastapi_webserver-0.4.14.dist-info/RECORD
