Metadata-Version: 2.4
Name: fastapi-webserver
Version: 0.4.14
Summary: A simple FastAPI webserver with a bunch of useful resources.
Author-email: Artemis Resende <artemis@aresende.com>
License: # 🏳️‍🌈 Opinionated Queer License v1.1
Project-URL: Homepage, https://gitlab.com/aresende/fastapi-webserver
Keywords: webserver,fastapi,quickstart
Classifier: Development Status :: 3 - Alpha
Classifier: Framework :: FastAPI
Classifier: Intended Audience :: Developers
Classifier: Topic :: Internet :: WWW/HTTP :: HTTP Servers
Classifier: Programming Language :: Python :: 3.13
Requires-Python: >=3.13
License-File: LICENSE.md
Requires-Dist: fastapi[standard]>=0.115.8
Requires-Dist: fastapi-mail>=1.4.2
Requires-Dist: email-validator>=2.2.0
Requires-Dist: pydantic-settings>=2.7.1
Requires-Dist: jinja2>=3.1.5
Requires-Dist: sqlmodel>=0.0.22
Requires-Dist: starlette>=0.45.3
Requires-Dist: command-runner>=1.7.0
Requires-Dist: httpx>=0.28.1
Requires-Dist: commons-library>=0.5.3
Dynamic: license-file
